pyhap/__init__.py
pyhap/accessory.py
pyhap/accessory_driver.py
pyhap/camera.py
pyhap/chacha20poly1305_adapter.py
pyhap/characteristic.py
pyhap/const.py
pyhap/crypto_adapter.py
pyhap/encoder.py
pyhap/hap_crypto.py
pyhap/hap_event.py
pyhap/hap_handler.py
pyhap/hap_protocol.py
pyhap/hap_server.py
pyhap/hsrp.py
pyhap/iid_manager.py
pyhap/json_adapter.py
pyhap/loader.py
pyhap/params.py
pyhap/service.py
pyhap/state.py
pyhap/tlv.py
pyhap/util.py
pyhap/resources/characteristics.json
pyhap/resources/services.json
pyhap/resources/snapshot.jpg
hap_python_pycryptodome-4.9.8.dist-info/LICENSE
hap_python_pycryptodome-4.9.8.dist-info/METADATA
hap_python_pycryptodome-4.9.8.dist-info/WHEEL
hap_python_pycryptodome-4.9.8.dist-info/top_level.txt
hap_python_pycryptodome-4.9.8.dist-info/RECORD
