Metadata-Version: 2.1
Name: HAP-python-pycryptodome
Version: 4.9.8
Summary: HomeKit Accessory Protocol implementation in python
Home-page: https://github.com/Zrincet/HAP-python-pycryptodome
License: Apache-2.0
Project-URL: Bug Reports, https://github.com/Zrincet/HAP-python-pycryptodome/issues
Project-URL: Documentation, http://hap-python.readthedocs.io/en/latest/
Project-URL: Source, https://github.com/Zrincet/HAP-python-pycryptodome/tree/master
Classifier: Development Status :: 5 - Production/Stable
Classifier: Intended Audience :: Developers
Classifier: Intended Audience :: End Users/Desktop
Classifier: License :: OSI Approved :: Apache Software License
Classifier: Natural Language :: English
Classifier: Operating System :: OS Independent
Classifier: Programming Language :: Python :: 3.5
Classifier: Programming Language :: Python :: 3.6
Classifier: Programming Language :: Python :: 3.7
Classifier: Programming Language :: Python :: 3.8
Classifier: Programming Language :: Python :: 3.9
Classifier: Programming Language :: Python :: 3.10
Classifier: Topic :: Home Automation
Classifier: Topic :: Software Development :: Libraries :: Python Modules
Requires-Python: >=3.7
License-File: LICENSE
Requires-Dist: async-timeout
Requires-Dist: pycryptodome==3.23.0
Requires-Dist: tlslite-ng==0.8.2
Requires-Dist: zeroconf==0.36.2
Requires-Dist: h11
Requires-Dist: base36
Provides-Extra: qrcode
Requires-Dist: base36; extra == "qrcode"
Requires-Dist: pyqrcode; extra == "qrcode"
